{"nodes": [{"id": "main", "label": "main.rs", "file_type": "code", "source_file": "src\\main.rs", "source_location": "L1"}, {"id": "main_state", "label": "State", "file_type": "code", "source_file": "src\\main.rs", "source_location": "L61"}, {"id": "main_anim", "label": "Anim", "file_type": "code", "source_file": "src\\main.rs", "source_location": "L92"}, {"id": "main_sendhwnd", "label": "SendHwnd", "file_type": "code", "source_file": "src\\main.rs", "source_location": "L100"}, {"id": "main_state_win_h", "label": ".win_h()", "file_type": "code", "source_file": "src\\main.rs", "source_location": "L105"}, {"id": "main_state_result_rect", "label": ".result_rect()", "file_type": "code", "source_file": "src\\main.rs", "source_location": "L109"}, {"id": "main_state_current_p", "label": ".current_p()", "file_type": "code", "source_file": "src\\main.rs", "source_location": "L115"}, {"id": "main_main", "label": "main()", "file_type": "code", "source_file": "src\\main.rs", "source_location": "L132"}, {"id": "main_run", "label": "run()", "file_type": "code", "source_file": "src\\main.rs", "source_location": "L141"}, {"id": "main_wnd_proc", "label": "wnd_proc()", "file_type": "code", "source_file": "src\\main.rs", "source_location": "L320"}, {"id": "main_animate_window", "label": "animate_window()", "file_type": "code", "source_file": "src\\main.rs", "source_location": "L776"}, {"id": "main_do_show", "label": "do_show()", "file_type": "code", "source_file": "src\\main.rs", "source_location": "L873"}, {"id": "main_start_hide", "label": "start_hide()", "file_type": "code", "source_file": "src\\main.rs", "source_location": "L877"}, {"id": "main_do_hide", "label": "do_hide()", "file_type": "code", "source_file": "src\\main.rs", "source_location": "L881"}, {"id": "main_kick_debounce", "label": "kick_debounce()", "file_type": "code", "source_file": "src\\main.rs", "source_location": "L887"}, {"id": "main_ease_out", "label": "ease_out()", "file_type": "code", "source_file": "src\\main.rs", "source_location": "L892"}, {"id": "main_ease_in", "label": "ease_in()", "file_type": "code", "source_file": "src\\main.rs", "source_location": "L893"}, {"id": "main_fill_rounded", "label": "fill_rounded()", "file_type": "code", "source_file": "src\\main.rs", "source_location": "L895"}, {"id": "main_resolve_lnk", "label": "resolve_lnk()", "file_type": "code", "source_file": "src\\main.rs", "source_location": "L910"}, {"id": "main_get_app_icon", "label": "get_app_icon()", "file_type": "code", "source_file": "src\\main.rs", "source_location": "L929"}, {"id": "main_get_file_icon", "label": "get_file_icon()", "file_type": "code", "source_file": "src\\main.rs", "source_location": "L1052"}, {"id": "main_trigger_icon_loading", "label": "trigger_icon_loading()", "file_type": "code", "source_file": "src\\main.rs", "source_location": "L1066"}, {"id": "main_paint", "label": "paint()", "file_type": "code", "source_file": "src\\main.rs", "source_location": "L1110"}, {"id": "main_fill", "label": "fill()", "file_type": "code", "source_file": "src\\main.rs", "source_location": "L1318"}, {"id": "main_draw_rounded_border_and_bg", "label": "draw_rounded_border_and_bg()", "file_type": "code", "source_file": "src\\main.rs", "source_location": "L1324"}, {"id": "main_badge", "label": "badge()", "file_type": "code", "source_file": "src\\main.rs", "source_location": "L1368"}, {"id": "main_load_icon_from_dll", "label": "load_icon_from_dll()", "file_type": "code", "source_file": "src\\main.rs", "source_location": "L1422"}, {"id": "main_load_icon_from_memory", "label": "load_icon_from_memory()", "file_type": "code", "source_file": "src\\main.rs", "source_location": "L1448"}, {"id": "main_get_active_app_name", "label": "get_active_app_name()", "file_type": "code", "source_file": "src\\main.rs", "source_location": "L1501"}, {"id": "main_copy_image_to_clipboard", "label": "copy_image_to_clipboard()", "file_type": "code", "source_file": "src\\main.rs", "source_location": "L1537"}, {"id": "main_capture_clipboard_image_data", "label": "capture_clipboard_image_data()", "file_type": "code", "source_file": "src\\main.rs", "source_location": "L1562"}, {"id": "main_write_bmp_file", "label": "write_bmp_file()", "file_type": "code", "source_file": "src\\main.rs", "source_location": "L1630"}, {"id": "main_import_windows_clipboard_history", "label": "import_windows_clipboard_history()", "file_type": "code", "source_file": "src\\main.rs", "source_location": "L1658"}, {"id": "main_copy_to_clipboard", "label": "copy_to_clipboard()", "file_type": "code", "source_file": "src\\main.rs", "source_location": "L1748"}, {"id": "main_paste_from_clipboard", "label": "paste_from_clipboard()", "file_type": "code", "source_file": "src\\main.rs", "source_location": "L1768"}, {"id": "main_start_timeline_tracker", "label": "start_timeline_tracker()", "file_type": "code", "source_file": "src\\main.rs", "source_location": "L1797"}, {"id": "main_log_timeline_event", "label": "log_timeline_event()", "file_type": "code", "source_file": "src\\main.rs", "source_location": "L1881"}, {"id": "main_load_bmp_file", "label": "load_bmp_file()", "file_type": "code", "source_file": "src\\main.rs", "source_location": "L1895"}, {"id": "main_draw_cached_bmp", "label": "draw_cached_bmp()", "file_type": "code", "source_file": "src\\main.rs", "source_location": "L1912"}, {"id": "main_test_winrt_clipboard", "label": "test_winrt_clipboard()", "file_type": "code", "source_file": "src\\main.rs", "source_location": "L1947"}, {"id": "main_test_antigravity_icons", "label": "test_antigravity_icons()", "file_type": "code", "source_file": "src\\main.rs", "source_location": "L1964"}, {"id": "main_test_image_factory_cast", "label": "test_image_factory_cast()", "file_type": "code", "source_file": "src\\main.rs", "source_location": "L1983"}], "edges": [{"source": "main", "target": "null_mut", "relation": "imports_from", "confidence": "EXTRACTED", "source_file": "src\\main.rs", "source_location": "L9", "weight": 1.0}, {"source": "main", "target": "search", "relation": "imports_from", "confidence": "EXTRACTED", "source_file": "src\\main.rs", "source_location": "L10", "weight": 1.0}, {"source": "main", "target": "windows", "relation": "imports_from", "confidence": "EXTRACTED", "source_file": "src\\main.rs", "source_location": "L11", "weight": 1.0}, {"source": "main", "target": "main_state", "relation": "contains", "confidence": "EXTRACTED", "source_file": "src\\main.rs", "source_location": "L61", "weight": 1.0}, {"source": "main", "target": "main_anim", "relation": "contains", "confidence": "EXTRACTED", "source_file": "src\\main.rs", "source_location": "L92", "weight": 1.0}, {"source": "main", "target": "main_sendhwnd", "relation": "contains", "confidence": "EXTRACTED", "source_file": "src\\main.rs", "source_location": "L100", "weight": 1.0}, {"source": "main_state", "target": "main_state_win_h", "relation": "method", "confidence": "EXTRACTED", "source_file": "src\\main.rs", "source_location": "L105", "weight": 1.0}, {"source": "main_state", "target": "main_state_result_rect", "relation": "method", "confidence": "EXTRACTED", "source_file": "src\\main.rs", "source_location": "L109", "weight": 1.0}, {"source": "main_state", "target": "main_state_current_p", "relation": "method", "confidence": "EXTRACTED", "source_file": "src\\main.rs", "source_location": "L115", "weight": 1.0}, {"source": "main", "target": "main_main", "relation": "contains", "confidence": "EXTRACTED", "source_file": "src\\main.rs", "source_location": "L132", "weight": 1.0}, {"source": "main", "target": "main_run", "relation": "contains", "confidence": "EXTRACTED", "source_file": "src\\main.rs", "source_location": "L141", "weight": 1.0}, {"source": "main", "target": "main_wnd_proc", "relation": "contains", "confidence": "EXTRACTED", "source_file": "src\\main.rs", "source_location": "L320", "weight": 1.0}, {"source": "main", "target": "main_animate_window", "relation": "contains", "confidence": "EXTRACTED", "source_file": "src\\main.rs", "source_location": "L776", "weight": 1.0}, {"source": "main", "target": "main_do_show", "relation": "contains", "confidence": "EXTRACTED", "source_file": "src\\main.rs", "source_location": "L873", "weight": 1.0}, {"source": "main", "target": "main_start_hide", "relation": "contains", "confidence": "EXTRACTED", "source_file": "src\\main.rs", "source_location": "L877", "weight": 1.0}, {"source": "main", "target": "main_do_hide", "relation": "contains", "confidence": "EXTRACTED", "source_file": "src\\main.rs", "source_location": "L881", "weight": 1.0}, {"source": "main", "target": "main_kick_debounce", "relation": "contains", "confidence": "EXTRACTED", "source_file": "src\\main.rs", "source_location": "L887", "weight": 1.0}, {"source": "main", "target": "main_ease_out", "relation": "contains", "confidence": "EXTRACTED", "source_file": "src\\main.rs", "source_location": "L892", "weight": 1.0}, {"source": "main", "target": "main_ease_in", "relation": "contains", "confidence": "EXTRACTED", "source_file": "src\\main.rs", "source_location": "L893", "weight": 1.0}, {"source": "main", "target": "main_fill_rounded", "relation": "contains", "confidence": "EXTRACTED", "source_file": "src\\main.rs", "source_location": "L895", "weight": 1.0}, {"source": "main", "target": "main_resolve_lnk", "relation": "contains", "confidence": "EXTRACTED", "source_file": "src\\main.rs", "source_location": "L910", "weight": 1.0}, {"source": "main", "target": "main_get_app_icon", "relation": "contains", "confidence": "EXTRACTED", "source_file": "src\\main.rs", "source_location": "L929", "weight": 1.0}, {"source": "main", "target": "main_get_file_icon", "relation": "contains", "confidence": "EXTRACTED", "source_file": "src\\main.rs", "source_location": "L1052", "weight": 1.0}, {"source": "main", "target": "main_trigger_icon_loading", "relation": "contains", "confidence": "EXTRACTED", "source_file": "src\\main.rs", "source_location": "L1066", "weight": 1.0}, {"source": "main", "target": "main_paint", "relation": "contains", "confidence": "EXTRACTED", "source_file": "src\\main.rs", "source_location": "L1110", "weight": 1.0}, {"source": "main", "target": "main_fill", "relation": "contains", "confidence": "EXTRACTED", "source_file": "src\\main.rs", "source_location": "L1318", "weight": 1.0}, {"source": "main", "target": "main_draw_rounded_border_and_bg", "relation": "contains", "confidence": "EXTRACTED", "source_file": "src\\main.rs", "source_location": "L1324", "weight": 1.0}, {"source": "main", "target": "main_badge", "relation": "contains", "confidence": "EXTRACTED", "source_file": "src\\main.rs", "source_location": "L1368", "weight": 1.0}, {"source": "main", "target": "main_load_icon_from_dll", "relation": "contains", "confidence": "EXTRACTED", "source_file": "src\\main.rs", "source_location": "L1422", "weight": 1.0}, {"source": "main", "target": "main_load_icon_from_memory", "relation": "contains", "confidence": "EXTRACTED", "source_file": "src\\main.rs", "source_location": "L1448", "weight": 1.0}, {"source": "main", "target": "main_get_active_app_name", "relation": "contains", "confidence": "EXTRACTED", "source_file": "src\\main.rs", "source_location": "L1501", "weight": 1.0}, {"source": "main", "target": "main_copy_image_to_clipboard", "relation": "contains", "confidence": "EXTRACTED", "source_file": "src\\main.rs", "source_location": "L1537", "weight": 1.0}, {"source": "main", "target": "main_capture_clipboard_image_data", "relation": "contains", "confidence": "EXTRACTED", "source_file": "src\\main.rs", "source_location": "L1562", "weight": 1.0}, {"source": "main", "target": "main_write_bmp_file", "relation": "contains", "confidence": "EXTRACTED", "source_file": "src\\main.rs", "source_location": "L1630", "weight": 1.0}, {"source": "main", "target": "main_import_windows_clipboard_history", "relation": "contains", "confidence": "EXTRACTED", "source_file": "src\\main.rs", "source_location": "L1658", "weight": 1.0}, {"source": "main", "target": "main_copy_to_clipboard", "relation": "contains", "confidence": "EXTRACTED", "source_file": "src\\main.rs", "source_location": "L1748", "weight": 1.0}, {"source": "main", "target": "main_paste_from_clipboard", "relation": "contains", "confidence": "EXTRACTED", "source_file": "src\\main.rs", "source_location": "L1768", "weight": 1.0}, {"source": "main", "target": "main_start_timeline_tracker", "relation": "contains", "confidence": "EXTRACTED", "source_file": "src\\main.rs", "source_location": "L1797", "weight": 1.0}, {"source": "main", "target": "main_log_timeline_event", "relation": "contains", "confidence": "EXTRACTED", "source_file": "src\\main.rs", "source_location": "L1881", "weight": 1.0}, {"source": "main", "target": "main_load_bmp_file", "relation": "contains", "confidence": "EXTRACTED", "source_file": "src\\main.rs", "source_location": "L1895", "weight": 1.0}, {"source": "main", "target": "main_draw_cached_bmp", "relation": "contains", "confidence": "EXTRACTED", "source_file": "src\\main.rs", "source_location": "L1912", "weight": 1.0}, {"source": "main", "target": "super", "relation": "imports_from", "confidence": "EXTRACTED", "source_file": "src\\main.rs", "source_location": "L1944", "weight": 1.0}, {"source": "main", "target": "main_test_winrt_clipboard", "relation": "contains", "confidence": "EXTRACTED", "source_file": "src\\main.rs", "source_location": "L1947", "weight": 1.0}, {"source": "main", "target": "main_test_antigravity_icons", "relation": "contains", "confidence": "EXTRACTED", "source_file": "src\\main.rs", "source_location": "L1964", "weight": 1.0}, {"source": "main", "target": "main_test_image_factory_cast", "relation": "contains", "confidence": "EXTRACTED", "source_file": "src\\main.rs", "source_location": "L1983", "weight": 1.0}, {"source": "main_state_result_rect", "target": "main_state_win_h", "relation": "calls", "confidence": "EXTRACTED", "source_file": "src\\main.rs", "source_location": "L110", "weight": 1.0}, {"source": "main_main", "target": "main_run", "relation": "calls", "confidence": "EXTRACTED", "source_file": "src\\main.rs", "source_location": "L138", "weight": 1.0}, {"source": "main_run", "target": "main_load_icon_from_memory", "relation": "calls", "confidence": "EXTRACTED", "source_file": "src\\main.rs", "source_location": "L161", "weight": 1.0}, {"source": "main_run", "target": "main_load_icon_from_dll", "relation": "calls", "confidence": "EXTRACTED", "source_file": "src\\main.rs", "source_location": "L165", "weight": 1.0}, {"source": "main_run", "target": "main_sendhwnd", "relation": "calls", "confidence": "EXTRACTED", "source_file": "src\\main.rs", "source_location": "L261", "weight": 1.0}, {"source": "main_run", "target": "main_start_timeline_tracker", "relation": "calls", "confidence": "EXTRACTED", "source_file": "src\\main.rs", "source_location": "L264", "weight": 1.0}, {"source": "main_run", "target": "main_import_windows_clipboard_history", "relation": "calls", "confidence": "EXTRACTED", "source_file": "src\\main.rs", "source_location": "L283", "weight": 1.0}, {"source": "main_wnd_proc", "target": "main_do_show", "relation": "calls", "confidence": "EXTRACTED", "source_file": "src\\main.rs", "source_location": "L335", "weight": 1.0}, {"source": "main_wnd_proc", "target": "main_start_hide", "relation": "calls", "confidence": "EXTRACTED", "source_file": "src\\main.rs", "source_location": "L336", "weight": 1.0}, {"source": "main_wnd_proc", "target": "main_get_active_app_name", "relation": "calls", "confidence": "EXTRACTED", "source_file": "src\\main.rs", "source_location": "L386", "weight": 1.0}, {"source": "main_wnd_proc", "target": "main_paste_from_clipboard", "relation": "calls", "confidence": "EXTRACTED", "source_file": "src\\main.rs", "source_location": "L389", "weight": 1.0}, {"source": "main_wnd_proc", "target": "main_capture_clipboard_image_data", "relation": "calls", "confidence": "EXTRACTED", "source_file": "src\\main.rs", "source_location": "L415", "weight": 1.0}, {"source": "main_wnd_proc", "target": "main_write_bmp_file", "relation": "calls", "confidence": "EXTRACTED", "source_file": "src\\main.rs", "source_location": "L428", "weight": 1.0}, {"source": "main_wnd_proc", "target": "main_trigger_icon_loading", "relation": "calls", "confidence": "EXTRACTED", "source_file": "src\\main.rs", "source_location": "L456", "weight": 1.0}, {"source": "main_wnd_proc", "target": "main_kick_debounce", "relation": "calls", "confidence": "EXTRACTED", "source_file": "src\\main.rs", "source_location": "L501", "weight": 1.0}, {"source": "main_wnd_proc", "target": "main_copy_to_clipboard", "relation": "calls", "confidence": "EXTRACTED", "source_file": "src\\main.rs", "source_location": "L527", "weight": 1.0}, {"source": "main_wnd_proc", "target": "main_do_hide", "relation": "calls", "confidence": "EXTRACTED", "source_file": "src\\main.rs", "source_location": "L577", "weight": 1.0}, {"source": "main_wnd_proc", "target": "main_copy_image_to_clipboard", "relation": "calls", "confidence": "EXTRACTED", "source_file": "src\\main.rs", "source_location": "L600", "weight": 1.0}, {"source": "main_wnd_proc", "target": "main_state_result_rect", "relation": "calls", "confidence": "EXTRACTED", "source_file": "src\\main.rs", "source_location": "L665", "weight": 1.0}, {"source": "main_wnd_proc", "target": "main_paint", "relation": "calls", "confidence": "EXTRACTED", "source_file": "src\\main.rs", "source_location": "L734", "weight": 1.0}, {"source": "main_animate_window", "target": "main_trigger_icon_loading", "relation": "calls", "confidence": "EXTRACTED", "source_file": "src\\main.rs", "source_location": "L800", "weight": 1.0}, {"source": "main_animate_window", "target": "main_ease_out", "relation": "calls", "confidence": "EXTRACTED", "source_file": "src\\main.rs", "source_location": "L836", "weight": 1.0}, {"source": "main_do_show", "target": "main_animate_window", "relation": "calls", "confidence": "EXTRACTED", "source_file": "src\\main.rs", "source_location": "L874", "weight": 1.0}, {"source": "main_start_hide", "target": "main_animate_window", "relation": "calls", "confidence": "EXTRACTED", "source_file": "src\\main.rs", "source_location": "L878", "weight": 1.0}, {"source": "main_get_app_icon", "target": "main_resolve_lnk", "relation": "calls", "confidence": "EXTRACTED", "source_file": "src\\main.rs", "source_location": "L936", "weight": 1.0}, {"source": "main_trigger_icon_loading", "target": "main_sendhwnd", "relation": "calls", "confidence": "EXTRACTED", "source_file": "src\\main.rs", "source_location": "L1079", "weight": 1.0}, {"source": "main_trigger_icon_loading", "target": "main_get_file_icon", "relation": "calls", "confidence": "EXTRACTED", "source_file": "src\\main.rs", "source_location": "L1088", "weight": 1.0}, {"source": "main_trigger_icon_loading", "target": "main_get_app_icon", "relation": "calls", "confidence": "EXTRACTED", "source_file": "src\\main.rs", "source_location": "L1090", "weight": 1.0}, {"source": "main_paint", "target": "main_fill", "relation": "calls", "confidence": "EXTRACTED", "source_file": "src\\main.rs", "source_location": "L1125", "weight": 1.0}, {"source": "main_paint", "target": "main_state_current_p", "relation": "calls", "confidence": "EXTRACTED", "source_file": "src\\main.rs", "source_location": "L1128", "weight": 1.0}, {"source": "main_paint", "target": "main_ease_out", "relation": "calls", "confidence": "EXTRACTED", "source_file": "src\\main.rs", "source_location": "L1129", "weight": 1.0}, {"source": "main_paint", "target": "main_state_win_h", "relation": "calls", "confidence": "EXTRACTED", "source_file": "src\\main.rs", "source_location": "L1137", "weight": 1.0}, {"source": "main_paint", "target": "main_draw_rounded_border_and_bg", "relation": "calls", "confidence": "EXTRACTED", "source_file": "src\\main.rs", "source_location": "L1148", "weight": 1.0}, {"source": "main_paint", "target": "main_draw_cached_bmp", "relation": "calls", "confidence": "EXTRACTED", "source_file": "src\\main.rs", "source_location": "L1216", "weight": 1.0}, {"source": "main_paint", "target": "main_load_bmp_file", "relation": "calls", "confidence": "EXTRACTED", "source_file": "src\\main.rs", "source_location": "L1220", "weight": 1.0}, {"source": "main_paint", "target": "main_badge", "relation": "calls", "confidence": "EXTRACTED", "source_file": "src\\main.rs", "source_location": "L1279", "weight": 1.0}, {"source": "main_draw_rounded_border_and_bg", "target": "main_fill_rounded", "relation": "calls", "confidence": "EXTRACTED", "source_file": "src\\main.rs", "source_location": "L1360", "weight": 1.0}, {"source": "main_badge", "target": "main_fill", "relation": "calls", "confidence": "EXTRACTED", "source_file": "src\\main.rs", "source_location": "L1413", "weight": 1.0}, {"source": "main_start_timeline_tracker", "target": "main_log_timeline_event", "relation": "calls", "confidence": "EXTRACTED", "source_file": "src\\main.rs", "source_location": "L1867", "weight": 1.0}, {"source": "main_test_antigravity_icons", "target": "main_get_app_icon", "relation": "calls", "confidence": "EXTRACTED", "source_file": "src\\main.rs", "source_location": "L1970", "weight": 1.0}]}